abx_plugin_ldap_auth/__init__.py
abx_plugin_ldap_auth/binaries.py
abx_plugin_ldap_auth/config.py
abx_plugin_ldap_auth-2024.10.28.dist-info/METADATA
abx_plugin_ldap_auth-2024.10.28.dist-info/WHEEL
abx_plugin_ldap_auth-2024.10.28.dist-info/entry_points.txt
abx_plugin_ldap_auth-2024.10.28.dist-info/RECORD
